{
  "_version": {
    "parser": "476d9d6507ee88061e8fa5d0ec9a0069fcefafe5",
    "raw": "397ae73f37cccc39e678f289840992fa70024208"
  },
  "away team": "SD",
  "betting": {
    "over under": 53.5,
    "spread": -7.0,
    "winner": "home"
  },
  "datetime": {
    "date": "2011-09-18",
    "duration": 11040,
    "start time": "16:15"
  },
  "home team": "NE",
  "officials": {
    "back judge": "Billy Smith",
    "field judge": "David Meslow",
    "head linesman": "Steve Stelljes",
    "line judge": "Byron Boston",
    "referee": "Walt Anderson",
    "side judge": "James Coleman",
    "umpire": "Butch Hannah"
  },
  "players": {
    "away": {
      "C": [
        "Nick Hardwick"
      ],
      "CB": [
        "Quentin Jammer",
        "Antoine Cason"
      ],
      "DT": [
        "Corey Liuget",
        "Antonio Garay"
      ],
      "FS": [
        "Eric Weddle"
      ],
      "G": [
        "Kris Dielman"
      ],
      "LB": [
        "Travis LaBoy",
        "Takeo Spikes",
        "Shaun Phillips",
        "Donald Butler"
      ],
      "LT": [
        "Marcus McNeill"
      ],
      "QB": [
        "Philip Rivers"
      ],
      "RB": [
        "Ryan Mathews"
      ],
      "RG": [
        "Louis Vasquez"
      ],
      "RT": [
        "Jeromey Clary"
      ],
      "SS": [
        "Bob Sanders"
      ],
      "TE": [
        "Antonio Gates",
        "Randy McMichael"
      ],
      "WR": [
        "Vincent Jackson",
        "Malcom Floyd"
      ]
    },
    "home": {
      "C": [
        "Daniel Connolly"
      ],
      "CB": [
        "Devin McCourty"
      ],
      "DB": [
        "Ras-I Dowling",
        "Josh Barrett"
      ],
      "DE": [
        "Shaun Ellis",
        "Andre Carter"
      ],
      "FS": [
        "Patrick Chung"
      ],
      "LB": [
        "Dane Fletcher",
        "Rob Ninkovich",
        "Jerod Mayo"
      ],
      "LG": [
        "Logan Mankins"
      ],
      "LT": [
        "Matt Light"
      ],
      "NT": [
        "Vince Wilfork"
      ],
      "QB": [
        "Tom Brady"
      ],
      "RB": [
        "Danny Woodhead"
      ],
      "RG": [
        "Brian Waters"
      ],
      "RT": [
        "Sebastian Vollmer"
      ],
      "SS": [
        "Sergio Brown"
      ],
      "TE": [
        "Rob Gronkowski",
        "Aaron Hernandez"
      ],
      "WR": [
        "Wes Welker",
        "Deion Branch"
      ]
    }
  },
  "plays": [
    {
      "number": 0,
      "play": {
        "type": "kick off"
      },
      "score": {
        "away": 0,
        "home": 0
      },
      "state": {
        "offense": "away",
        "time": 0,
        "yards to goal": 35
      }
    },
    {
      "number": 1,
      "play": {
        "type": "run"
      },
      "score": {
        "away": 0,
        "home": 0
      },
      "state": {
        "down": 1,
        "offense": "away",
        "time": 4,
        "yards to first down": 10,
        "yards to goal": 80
      }
    },
    {
      "number": 2,
      "play": {
        "type": "run"
      },
      "score": {
        "away": 0,
        "home": 0
      },
      "state": {
        "down": 2,
        "offense": "away",
        "time": 40,
        "yards to first down": 3,
        "yards to goal": 73
      }
    },
    {
      "number": 3,
      "penalty": {
        "no play": true,
        "penalties": [
          {
            "accepted": true,
            "name": "False Start",
            "offender": "Vincent Jackson",
            "team": "away",
            "yards": 5
          }
        ]
      },
      "play": {
        "type": "penalty"
      },
      "score": {
        "away": 0,
        "home": 0
      },
      "state": {
        "down": 1,
        "offense": "away",
        "time": 73,
        "yards to first down": 10,
        "yards to goal": 69
      }
    },
    {
      "number": 4,
      "play": {
        "type": "complete pass"
      },
      "score": {
        "away": 0,
        "home": 0
      },
      "state": {
        "down": 1,
        "offense": "away",
        "time": 95,
        "yards to first down": 15,
        "yards to goal": 74
      }
    },
    {
      "number": 5,
      "play": {
        "type": "run"
      },
      "score": {
        "away": 0,
        "home": 0
      },
      "state": {
        "down": 1,
        "offense": "away",
        "time": 122,
        "yards to first down": 10,
        "yards to goal": 45
      }
    },
    {
      "number": 6,
      "play": {
        "type": "incomplete pass"
      },
      "score": {
        "away": 0,
        "home": 0
      },
      "state": {
        "down": 2,
        "offense": "away",
        "time": 160,
        "yards to first down": 8,
        "yards to goal": 43
      }
    },
    {
      "number": 7,
      "play": {
        "type": "incomplete pass"
      },
      "score": {
        "away": 0,
        "home": 0
      },
      "state": {
        "down": 3,
        "offense": "away",
        "time": 164,
        "yards to first down": 8,
        "yards to goal": 43
      }
    },
    {
      "number": 8,
      "play": {
        "type": "punt"
      },
      "score": {
        "away": 0,
        "home": 0
      },
      "state": {
        "down": 4,
        "offense": "away",
        "time": 169,
        "yards to first down": 8,
        "yards to goal": 43
      }
    },
    {
      "number": 9,
      "play": {
        "type": "complete pass"
      },
      "score": {
        "away": 0,
        "home": 0
      },
      "state": {
        "down": 1,
        "offense": "home",
        "time": 177,
        "yards to first down": 10,
        "yards to goal": 92
      }
    },
    {
      "number": 10,
      "play": {
        "type": "run"
      },
      "score": {
        "away": 0,
        "home": 0
      },
      "state": {
        "down": 1,
        "offense": "home",
        "time": 224,
        "yards to first down": 10,
        "yards to goal": 81
      }
    },
    {
      "number": 11,
      "play": {
        "type": "sack"
      },
      "score": {
        "away": 0,
        "home": 0
      },
      "state": {
        "down": 2,
        "offense": "home",
        "time": 257,
        "yards to first down": 4,
        "yards to goal": 75
      }
    },
    {
      "number": 12,
      "play": {
        "type": "complete pass"
      },
      "score": {
        "away": 0,
        "home": 0
      },
      "state": {
        "down": 3,
        "offense": "home",
        "time": 290,
        "yards to first down": 10,
        "yards to goal": 81
      }
    },
    {
      "number": 13,
      "play": {
        "type": "complete pass"
      },
      "score": {
        "away": 0,
        "home": 0
      },
      "state": {
        "down": 1,
        "offense": "home",
        "time": 323,
        "yards to first down": 10,
        "yards to goal": 64
      }
    },
    {
      "number": 14,
      "play": {
        "type": "run"
      },
      "score": {
        "away": 0,
        "home": 0
      },
      "state": {
        "down": 1,
        "offense": "home",
        "time": 350,
        "yards to first down": 10,
        "yards to goal": 48
      }
    },
    {
      "number": 15,
      "play": {
        "type": "complete pass"
      },
      "score": {
        "away": 0,
        "home": 0
      },
      "state": {
        "down": 2,
        "offense": "home",
        "time": 389,
        "yards to first down": 7,
        "yards to goal": 45
      }
    },
    {
      "number": 16,
      "play": {
        "type": "timeout"
      },
      "score": {
        "away": 0,
        "home": 0
      },
      "state": {
        "offense": "home",
        "time": 422
      }
    },
    {
      "number": 17,
      "play": {
        "type": "run"
      },
      "score": {
        "away": 0,
        "home": 0
      },
      "state": {
        "down": 3,
        "offense": "home",
        "time": 422,
        "yards to first down": 2,
        "yards to goal": 40
      }
    },
    {
      "number": 18,
      "play": {
        "type": "run"
      },
      "score": {
        "away": 0,
        "home": 0
      },
      "state": {
        "down": 1,
        "offense": "home",
        "time": 450,
        "yards to first down": 10,
        "yards to goal": 34
      }
    },
    {
      "number": 19,
      "play": {
        "type": "incomplete pass"
      },
      "score": {
        "away": 0,
        "home": 0
      },
      "state": {
        "down": 2,
        "offense": "home",
        "time": 487,
        "yards to first down": 5,
        "yards to goal": 29
      }
    },
    {
      "number": 20,
      "penalty": {
        "no play": false,
        "penalties": [
          {
            "accepted": false,
            "name": "Defensive Pass Interference",
            "offender": "Antoine Cason",
            "team": "away"
          }
        ]
      },
      "play": {
        "type": "complete pass"
      },
      "score": {
        "away": 0,
        "home": 0
      },
      "state": {
        "down": 3,
        "offense": "home",
        "time": 492,
        "yards to first down": 5,
        "yards to goal": 29
      }
    },
    {
      "number": 21,
      "play": {
        "scoring": {
          "team": "home",
          "type": "touchdown"
        },
        "type": "complete pass"
      },
      "score": {
        "away": 0,
        "home": 6
      },
      "state": {
        "down": 1,
        "offense": "home",
        "time": 518,
        "yards to first down": 10,
        "yards to goal": 14
      }
    },
    {
      "number": 22,
      "play": {
        "scoring": {
          "team": "home",
          "type": "extra point"
        },
        "type": "extra point"
      },
      "score": {
        "away": 0,
        "home": 7
      },
      "state": {
        "offense": "home",
        "time": 518
      }
    },
    {
      "number": 23,
      "play": {
        "type": "kick off"
      },
      "score": {
        "away": 0,
        "home": 7
      },
      "state": {
        "offense": "away",
        "time": 518,
        "yards to goal": 35
      }
    },
    {
      "number": 24,
      "play": {
        "type": "complete pass"
      },
      "score": {
        "away": 0,
        "home": 7
      },
      "state": {
        "down": 1,
        "offense": "away",
        "time": 524,
        "yards to first down": 10,
        "yards to goal": 80
      }
    },
    {
      "number": 25,
      "play": {
        "type": "incomplete pass"
      },
      "score": {
        "away": 0,
        "home": 7
      },
      "state": {
        "down": 2,
        "offense": "away",
        "time": 564,
        "yards to first down": 5,
        "yards to goal": 75
      }
    },
    {
      "number": 26,
      "play": {
        "type": "complete pass"
      },
      "score": {
        "away": 0,
        "home": 7
      },
      "state": {
        "down": 3,
        "offense": "away",
        "time": 570,
        "yards to first down": 5,
        "yards to goal": 75
      }
    },
    {
      "number": 27,
      "play": {
        "type": "run"
      },
      "score": {
        "away": 0,
        "home": 7
      },
      "state": {
        "down": 1,
        "offense": "away",
        "time": 611,
        "yards to first down": 10,
        "yards to goal": 52
      }
    },
    {
      "number": 28,
      "play": {
        "type": "run"
      },
      "score": {
        "away": 0,
        "home": 7
      },
      "state": {
        "down": 2,
        "offense": "away",
        "time": 647,
        "yards to first down": 5,
        "yards to goal": 47
      }
    },
    {
      "number": 29,
      "play": {
        "type": "complete pass"
      },
      "score": {
        "away": 0,
        "home": 7
      },
      "state": {
        "down": 3,
        "offense": "away",
        "time": 685,
        "yards to first down": 4,
        "yards to goal": 46
      }
    },
    {
      "number": 30,
      "play": {
        "scoring": {
          "team": "away",
          "type": "touchdown"
        },
        "type": "run"
      },
      "score": {
        "away": 6,
        "home": 7
      },
      "state": {
        "down": 1,
        "offense": "away",
        "time": 721,
        "yards to first down": 10,
        "yards to goal": 10
      }
    },
    {
      "number": 31,
      "play": {
        "scoring": {
          "team": "away",
          "type": "extra point"
        },
        "type": "extra point"
      },
      "score": {
        "away": 7,
        "home": 7
      },
      "state": {
        "offense": "away",
        "time": 721
      }
    },
    {
      "number": 32,
      "play": {
        "type": "kick off"
      },
      "score": {
        "away": 7,
        "home": 7
      },
      "state": {
        "offense": "home",
        "time": 721,
        "yards to goal": 35
      }
    },
    {
      "number": 33,
      "play": {
        "type": "run"
      },
      "score": {
        "away": 7,
        "home": 7
      },
      "state": {
        "down": 1,
        "offense": "home",
        "time": 730,
        "yards to first down": 10,
        "yards to goal": 63
      }
    },
    {
      "number": 34,
      "play": {
        "type": "run"
      },
      "score": {
        "away": 7,
        "home": 7
      },
      "state": {
        "down": 2,
        "offense": "home",
        "time": 763,
        "yards to first down": 6,
        "yards to goal": 59
      }
    },
    {
      "number": 35,
      "penalty": {
        "no play": false,
        "penalties": [
          {
            "accepted": false,
            "name": "Defensive Offside",
            "offender": "Antwan Barnes",
            "team": "away"
          }
        ]
      },
      "play": {
        "type": "complete pass"
      },
      "score": {
        "away": 7,
        "home": 7
      },
      "state": {
        "down": 3,
        "offense": "home",
        "time": 801,
        "yards to first down": 3,
        "yards to goal": 56
      }
    },
    {
      "number": 36,
      "penalty": {
        "no play": true,
        "penalties": [
          {
            "accepted": true,
            "name": "Offensive Holding",
            "offender": "Rob Gronkowski",
            "team": "home",
            "yards": 10
          }
        ]
      },
      "play": {
        "type": "run"
      },
      "score": {
        "away": 7,
        "home": 7
      },
      "state": {
        "down": 1,
        "offense": "home",
        "time": 808,
        "yards to first down": 10,
        "yards to goal": 47
      }
    },
    {
      "number": 37,
      "play": {
        "type": "complete pass"
      },
      "score": {
        "away": 7,
        "home": 7
      },
      "state": {
        "down": 1,
        "offense": "home",
        "time": 822,
        "yards to first down": 20,
        "yards to goal": 57
      }
    },
    {
      "number": 38,
      "play": {
        "type": "complete pass"
      },
      "score": {
        "away": 7,
        "home": 7
      },
      "state": {
        "down": 2,
        "offense": "home",
        "time": 852,
        "yards to first down": 14,
        "yards to goal": 51
      }
    },
    {
      "number": 39,
      "play": {
        "type": "complete pass"
      },
      "score": {
        "away": 7,
        "home": 7
      },
      "state": {
        "down": 3,
        "offense": "home",
        "time": 876,
        "yards to first down": 8,
        "yards to goal": 45
      }
    },
    {
      "number": 40,
      "play": {
        "type": "complete pass"
      },
      "score": {
        "away": 7,
        "home": 7
      },
      "state": {
        "down": 1,
        "offense": "home",
        "time": 893,
        "yards to first down": 10,
        "yards to goal": 28
      }
    },
    {
      "number": 41,
      "play": {
        "type": "complete pass"
      },
      "score": {
        "away": 7,
        "home": 7
      },
      "state": {
        "down": 2,
        "offense": "home",
        "time": 900,
        "yards to first down": 5,
        "yards to goal": 23
      }
    },
    {
      "number": 42,
      "play": {
        "type": "run"
      },
      "score": {
        "away": 7,
        "home": 7
      },
      "state": {
        "down": 1,
        "offense": "home",
        "time": 911,
        "yards to first down": 10,
        "yards to goal": 15
      }
    },
    {
      "number": 43,
      "penalty": {
        "no play": false,
        "penalties": [
          {
            "accepted": true,
            "name": "Illegal Contact",
            "offender": "Takeo Spikes",
            "team": "away",
            "yards": 4
          }
        ]
      },
      "play": {
        "type": "run"
      },
      "score": {
        "away": 7,
        "home": 7
      },
      "state": {
        "down": 2,
        "offense": "home",
        "time": 934,
        "yards to first down": 7,
        "yards to goal": 12
      }
    },
    {
      "number": 44,
      "play": {
        "type": "incomplete pass"
      },
      "score": {
        "away": 7,
        "home": 7
      },
      "state": {
        "down": 1,
        "offense": "home",
        "time": 952,
        "yards to first down": 4,
        "yards to goal": 4
      }
    },
    {
      "number": 45,
      "play": {
        "type": "run"
      },
      "score": {
        "away": 7,
        "home": 7
      },
      "state": {
        "down": 2,
        "offense": "home",
        "time": 956,
        "yards to first down": 4,
        "yards to goal": 4
      }
    },
    {
      "number": 46,
      "play": {
        "type": "incomplete pass"
      },
      "score": {
        "away": 7,
        "home": 7
      },
      "state": {
        "down": 3,
        "offense": "home",
        "time": 992,
        "yards to first down": 4,
        "yards to goal": 4
      }
    },
    {
      "number": 47,
      "play": {
        "scoring": {
          "team": "home",
          "type": "field goal"
        },
        "type": "field goal"
      },
      "score": {
        "away": 7,
        "home": 10
      },
      "state": {
        "down": 4,
        "offense": "home",
        "time": 997,
        "yards to first down": 4,
        "yards to goal": 4
      }
    },
    {
      "number": 48,
      "play": {
        "type": "kick off"
      },
      "score": {
        "away": 7,
        "home": 10
      },
      "state": {
        "offense": "away",
        "time": 997,
        "yards to goal": 35
      }
    },
    {
      "number": 49,
      "penalty": {
        "no play": true,
        "penalties": [
          {
            "accepted": true,
            "name": "Roughing the Passer",
            "offender": "Tony Carter",
            "team": "home",
            "yards": 15
          }
        ]
      },
      "play": {
        "type": "incomplete pass"
      },
      "score": {
        "away": 7,
        "home": 10
      },
      "state": {
        "down": 1,
        "offense": "away",
        "time": 1004,
        "yards to first down": 10,
        "yards to goal": 76
      }
    },
    {
      "number": 50,
      "play": {
        "type": "run"
      },
      "score": {
        "away": 7,
        "home": 10
      },
      "state": {
        "down": 1,
        "offense": "away",
        "time": 1010,
        "yards to first down": 10,
        "yards to goal": 61
      }
    },
    {
      "number": 51,
      "play": {
        "type": "run"
      },
      "score": {
        "away": 7,
        "home": 10
      },
      "state": {
        "down": 2,
        "offense": "away",
        "time": 1048,
        "yards to first down": 5,
        "yards to goal": 56
      }
    },
    {
      "number": 52,
      "play": {
        "type": "complete pass"
      },
      "score": {
        "away": 7,
        "home": 10
      },
      "state": {
        "down": 3,
        "offense": "away",
        "time": 1090,
        "yards to first down": 3,
        "yards to goal": 54
      }
    },
    {
      "number": 53,
      "play": {
        "type": "complete pass"
      },
      "score": {
        "away": 7,
        "home": 10
      },
      "state": {
        "down": 1,
        "offense": "away",
        "time": 1136,
        "yards to first down": 10,
        "yards to goal": 26
      }
    },
    {
      "number": 54,
      "play": {
        "type": "run"
      },
      "score": {
        "away": 7,
        "home": 10
      },
      "state": {
        "down": 1,
        "offense": "away",
        "time": 1184,
        "yards to first down": 5,
        "yards to goal": 5
      }
    },
    {
      "number": 55,
      "play": {
        "type": "run"
      },
      "score": {
        "away": 7,
        "home": 10
      },
      "state": {
        "down": 2,
        "offense": "away",
        "time": 1216,
        "yards to first down": 2,
        "yards to goal": 2
      }
    },
    {
      "number": 56,
      "play": {
        "type": "timeout"
      },
      "score": {
        "away": 7,
        "home": 10
      },
      "state": {
        "offense": "away",
        "time": 1259
      }
    },
    {
      "number": 57,
      "play": {
        "type": "run"
      },
      "score": {
        "away": 7,
        "home": 10
      },
      "state": {
        "down": 3,
        "offense": "away",
        "time": 1259,
        "yards to first down": 2,
        "yards to goal": 2
      }
    },
    {
      "number": 58,
      "play": {
        "type": "run"
      },
      "score": {
        "away": 7,
        "home": 10
      },
      "state": {
        "down": 4,
        "offense": "away",
        "time": 1303,
        "yards to first down": 1,
        "yards to goal": 1
      }
    },
    {
      "number": 59,
      "play": {
        "type": "complete pass"
      },
      "score": {
        "away": 7,
        "home": 10
      },
      "state": {
        "down": 1,
        "offense": "home",
        "time": 1306,
        "yards to first down": 10,
        "yards to goal": 99
      }
    },
    {
      "number": 60,
      "play": {
        "type": "complete pass"
      },
      "score": {
        "away": 7,
        "home": 10
      },
      "state": {
        "down": 1,
        "offense": "home",
        "time": 1348,
        "yards to first down": 10,
        "yards to goal": 87
      }
    },
    {
      "number": 61,
      "play": {
        "type": "sack"
      },
      "score": {
        "away": 7,
        "home": 10
      },
      "state": {
        "down": 1,
        "offense": "home",
        "time": 1394,
        "yards to first down": 10,
        "yards to goal": 57
      }
    },
    {
      "number": 62,
      "play": {
        "type": "complete pass"
      },
      "score": {
        "away": 7,
        "home": 10
      },
      "state": {
        "down": 2,
        "offense": "home",
        "time": 1426,
        "yards to first down": 17,
        "yards to goal": 64
      }
    },
    {
      "number": 63,
      "play": {
        "type": "run"
      },
      "score": {
        "away": 7,
        "home": 10
      },
      "state": {
        "down": 1,
        "offense": "home",
        "time": 1463,
        "yards to first down": 10,
        "yards to goal": 44
      }
    },
    {
      "number": 64,
      "play": {
        "type": "run"
      },
      "score": {
        "away": 7,
        "home": 10
      },
      "state": {
        "down": 2,
        "offense": "home",
        "time": 1498,
        "yards to first down": 4,
        "yards to goal": 38
      }
    },
    {
      "number": 65,
      "play": {
        "type": "complete pass"
      },
      "score": {
        "away": 7,
        "home": 10
      },
      "state": {
        "down": 3,
        "offense": "home",
        "time": 1538,
        "yards to first down": 1,
        "yards to goal": 35
      }
    },
    {
      "number": 66,
      "play": {
        "type": "run"
      },
      "score": {
        "away": 7,
        "home": 10
      },
      "state": {
        "down": 1,
        "offense": "home",
        "time": 1571,
        "yards to first down": 10,
        "yards to goal": 33
      }
    },
    {
      "number": 67,
      "play": {
        "type": "complete pass"
      },
      "score": {
        "away": 7,
        "home": 10
      },
      "state": {
        "down": 2,
        "offense": "home",
        "time": 1596,
        "yards to first down": 6,
        "yards to goal": 29
      }
    },
    {
      "number": 68,
      "play": {
        "scoring": {
          "team": "home",
          "type": "touchdown"
        },
        "type": "complete pass"
      },
      "score": {
        "away": 7,
        "home": 16
      },
      "state": {
        "down": 1,
        "offense": "home",
        "time": 1628,
        "yards to first down": 10,
        "yards to goal": 10
      }
    },
    {
      "number": 69,
      "play": {
        "scoring": {
          "team": "home",
          "type": "extra point"
        },
        "type": "extra point"
      },
      "score": {
        "away": 7,
        "home": 17
      },
      "state": {
        "offense": "home",
        "time": 1628
      }
    },
    {
      "number": 70,
      "play": {
        "type": "kick off"
      },
      "score": {
        "away": 7,
        "home": 17
      },
      "state": {
        "offense": "away",
        "time": 1628
      }
    },
    {
      "number": 71,
      "penalty": {
        "no play": false,
        "penalties": [
          {
            "accepted": true,
            "name": "Offensive Holding",
            "offender": "Jacob Hester",
            "team": "away",
            "yards": 10
          }
        ]
      },
      "play": {
        "type": "run"
      },
      "score": {
        "away": 7,
        "home": 17
      },
      "state": {
        "down": 1,
        "offense": "away",
        "time": 1631,
        "yards to first down": 10,
        "yards to goal": 80
      }
    },
    {
      "number": 72,
      "play": {
        "type": "complete pass"
      },
      "score": {
        "away": 7,
        "home": 17
      },
      "state": {
        "down": 1,
        "offense": "away",
        "time": 1663,
        "yards to first down": 13,
        "yards to goal": 83
      }
    },
    {
      "number": 73,
      "play": {
        "type": "incomplete pass"
      },
      "score": {
        "away": 7,
        "home": 17
      },
      "state": {
        "down": 2,
        "offense": "away",
        "time": 1680,
        "yards to first down": 7,
        "yards to goal": 77
      }
    },
    {
      "number": 74,
      "play": {
        "type": "complete pass"
      },
      "score": {
        "away": 7,
        "home": 17
      },
      "state": {
        "down": 3,
        "offense": "away",
        "time": 1683,
        "yards to first down": 7,
        "yards to goal": 77
      }
    },
    {
      "number": 75,
      "play": {
        "type": "timeout"
      },
      "score": {
        "away": 7,
        "home": 17
      },
      "state": {
        "offense": "away",
        "time": 1698
      }
    },
    {
      "number": 76,
      "play": {
        "type": "complete pass"
      },
      "score": {
        "away": 7,
        "home": 17
      },
      "state": {
        "down": 1,
        "offense": "away",
        "time": 1698,
        "yards to first down": 10,
        "yards to goal": 70
      }
    },
    {
      "number": 77,
      "play": {
        "type": "incomplete pass"
      },
      "score": {
        "away": 7,
        "home": 17
      },
      "state": {
        "down": 2,
        "offense": "away",
        "time": 1729,
        "yards to first down": 4,
        "yards to goal": 64
      }
    },
    {
      "number": 78,
      "penalty": {
        "no play": true,
        "penalties": [
          {
            "accepted": true,
            "name": "Defensive Holding",
            "offender": "Leigh Bodden",
            "team": "home",
            "yards": 5
          }
        ]
      },
      "play": {
        "type": "incomplete pass"
      },
      "score": {
        "away": 7,
        "home": 17
      },
      "state": {
        "down": 3,
        "offense": "away",
        "time": 1736,
        "yards to first down": 4,
        "yards to goal": 64
      }
    },
    {
      "number": 79,
      "play": {
        "type": "complete pass"
      },
      "score": {
        "away": 7,
        "home": 17
      },
      "state": {
        "down": 1,
        "offense": "away",
        "time": 1743,
        "yards to first down": 10,
        "yards to goal": 59
      }
    },
    {
      "number": 80,
      "play": {
        "type": "incomplete pass"
      },
      "score": {
        "away": 7,
        "home": 17
      },
      "state": {
        "down": 1,
        "offense": "away",
        "time": 1769,
        "yards to first down": 10,
        "yards to goal": 41
      }
    },
    {
      "number": 81,
      "play": {
        "type": "timeout"
      },
      "score": {
        "away": 7,
        "home": 17
      },
      "state": {
        "offense": "away",
        "time": 1773
      }
    },
    {
      "number": 82,
      "penalty": {
        "no play": true,
        "penalties": [
          {
            "accepted": true,
            "name": "False Start",
            "offender": "Marcus McNeill",
            "team": "away",
            "yards": 5
          }
        ]
      },
      "play": {
        "type": "penalty"
      },
      "score": {
        "away": 7,
        "home": 17
      },
      "state": {
        "down": 2,
        "offense": "away",
        "time": 1773,
        "yards to first down": 10,
        "yards to goal": 41
      }
    },
    {
      "number": 83,
      "play": {
        "type": "complete pass"
      },
      "score": {
        "away": 7,
        "home": 17
      },
      "state": {
        "down": 2,
        "offense": "away",
        "time": 1773,
        "yards to first down": 15,
        "yards to goal": 46
      }
    },
    {
      "number": 84,
      "play": {
        "type": "timeout"
      },
      "score": {
        "away": 7,
        "home": 17
      },
      "state": {
        "offense": "away",
        "time": 1781
      }
    },
    {
      "number": 85,
      "penalty": {
        "no play": false,
        "penalties": [
          {
            "accepted": true,
            "name": "Illegal Block Above the Waist",
            "offender": "Devin McCourty",
            "team": "home",
            "yards": 10
          }
        ]
      },
      "play": {
        "type": "incomplete pass"
      },
      "score": {
        "away": 7,
        "home": 17
      },
      "state": {
        "down": 1,
        "offense": "away",
        "time": 1781,
        "yards to first down": 10,
        "yards to goal": 29
      },
      "turnovers": [
        {
          "by": "away",
          "recovered": "home",
          "type": "interception"
        }
      ]
    },
    {
      "number": 86,
      "play": {
        "type": "complete pass"
      },
      "score": {
        "away": 7,
        "home": 17
      },
      "state": {
        "down": 1,
        "offense": "home",
        "time": 1791,
        "yards to first down": 10,
        "yards to goal": 47
      }
    },
    {
      "number": 87,
      "play": {
        "type": "complete pass"
      },
      "score": {
        "away": 7,
        "home": 17
      },
      "state": {
        "down": 1,
        "offense": "home",
        "time": 1794,
        "yards to first down": 10,
        "yards to goal": 36
      }
    },
    {
      "number": 88,
      "play": {
        "scoring": {
          "team": "home",
          "type": "field goal"
        },
        "type": "field goal"
      },
      "score": {
        "away": 7,
        "home": 20
      },
      "state": {
        "down": 2,
        "offense": "home",
        "time": 1799,
        "yards to first down": 3,
        "yards to goal": 29
      }
    },
    {
      "number": 89,
      "play": {
        "type": "kick off"
      },
      "score": {
        "away": 7,
        "home": 20
      },
      "state": {
        "offense": "home",
        "time": 1799,
        "yards to goal": 35
      }
    },
    {
      "number": 90,
      "play": {
        "type": "complete pass"
      },
      "score": {
        "away": 7,
        "home": 20
      },
      "state": {
        "down": 1,
        "offense": "home",
        "time": 1805,
        "yards to first down": 10,
        "yards to goal": 85
      }
    },
    {
      "number": 91,
      "play": {
        "type": "run"
      },
      "score": {
        "away": 7,
        "home": 20
      },
      "state": {
        "down": 1,
        "offense": "home",
        "time": 1834,
        "yards to first down": 10,
        "yards to goal": 55
      }
    },
    {
      "number": 92,
      "play": {
        "type": "complete pass"
      },
      "score": {
        "away": 7,
        "home": 20
      },
      "state": {
        "down": 2,
        "offense": "home",
        "time": 1875,
        "yards to first down": 5,
        "yards to goal": 50
      }
    },
    {
      "number": 93,
      "play": {
        "type": "run"
      },
      "score": {
        "away": 7,
        "home": 20
      },
      "state": {
        "down": 1,
        "offense": "home",
        "time": 1905,
        "yards to first down": 10,
        "yards to goal": 42
      }
    },
    {
      "number": 94,
      "penalty": {
        "no play": true,
        "penalties": [
          {
            "accepted": true,
            "name": "False Start",
            "offender": "Dan Gronkowski",
            "team": "home",
            "yards": 5
          }
        ]
      },
      "play": {
        "type": "penalty"
      },
      "score": {
        "away": 7,
        "home": 20
      },
      "state": {
        "down": 2,
        "offense": "home",
        "time": 1946,
        "yards to first down": 11,
        "yards to goal": 43
      }
    },
    {
      "number": 95,
      "play": {
        "type": "complete pass"
      },
      "score": {
        "away": 7,
        "home": 20
      },
      "state": {
        "down": 2,
        "offense": "home",
        "time": 1971,
        "yards to first down": 16,
        "yards to goal": 48
      }
    },
    {
      "number": 96,
      "play": {
        "type": "incomplete pass"
      },
      "score": {
        "away": 7,
        "home": 20
      },
      "state": {
        "down": 3,
        "offense": "home",
        "time": 2015,
        "yards to first down": 5,
        "yards to goal": 37
      }
    },
    {
      "number": 97,
      "play": {
        "type": "punt"
      },
      "score": {
        "away": 7,
        "home": 20
      },
      "state": {
        "down": 4,
        "offense": "home",
        "time": 2020,
        "yards to first down": 5,
        "yards to goal": 37
      }
    },
    {
      "number": 98,
      "play": {
        "type": "run"
      },
      "score": {
        "away": 7,
        "home": 20
      },
      "state": {
        "down": 1,
        "offense": "away",
        "time": 2027,
        "yards to first down": 10,
        "yards to goal": 94
      }
    },
    {
      "number": 99,
      "play": {
        "type": "complete pass"
      },
      "score": {
        "away": 7,
        "home": 20
      },
      "state": {
        "down": 2,
        "offense": "away",
        "time": 2063,
        "yards to first down": 11,
        "yards to goal": 95
      }
    },
    {
      "number": 100,
      "play": {
        "type": "complete pass"
      },
      "score": {
        "away": 7,
        "home": 20
      },
      "state": {
        "down": 3,
        "offense": "away",
        "time": 2106,
        "yards to first down": 2,
        "yards to goal": 86
      }
    },
    {
      "number": 101,
      "play": {
        "type": "run"
      },
      "score": {
        "away": 7,
        "home": 20
      },
      "state": {
        "down": 1,
        "offense": "away",
        "time": 2141,
        "yards to first down": 10,
        "yards to goal": 78
      }
    },
    {
      "number": 102,
      "play": {
        "type": "complete pass"
      },
      "score": {
        "away": 7,
        "home": 20
      },
      "state": {
        "down": 2,
        "offense": "away",
        "time": 2175,
        "yards to first down": 7,
        "yards to goal": 75
      }
    },
    {
      "number": 103,
      "play": {
        "type": "run"
      },
      "score": {
        "away": 7,
        "home": 20
      },
      "state": {
        "down": 3,
        "offense": "away",
        "time": 2214,
        "yards to first down": 1,
        "yards to goal": 69
      }
    },
    {
      "number": 104,
      "play": {
        "type": "complete pass"
      },
      "score": {
        "away": 7,
        "home": 20
      },
      "state": {
        "down": 1,
        "offense": "away",
        "time": 2252,
        "yards to first down": 10,
        "yards to goal": 57
      }
    },
    {
      "number": 105,
      "penalty": {
        "no play": true,
        "penalties": [
          {
            "accepted": true,
            "name": "Defensive Holding",
            "offender": "Leigh Bodden",
            "team": "home",
            "yards": 5
          }
        ]
      },
      "play": {
        "type": "incomplete pass"
      },
      "score": {
        "away": 7,
        "home": 20
      },
      "state": {
        "down": 2,
        "offense": "away",
        "time": 2296,
        "yards to first down": 1,
        "yards to goal": 48
      }
    },
    {
      "number": 106,
      "play": {
        "type": "run"
      },
      "score": {
        "away": 7,
        "home": 20
      },
      "state": {
        "down": 1,
        "offense": "away",
        "time": 2303,
        "yards to first down": 10,
        "yards to goal": 43
      }
    },
    {
      "number": 107,
      "play": {
        "type": "run"
      },
      "score": {
        "away": 7,
        "home": 20
      },
      "state": {
        "down": 1,
        "offense": "away",
        "time": 2337,
        "yards to first down": 10,
        "yards to goal": 29
      }
    },
    {
      "number": 108,
      "play": {
        "type": "complete pass"
      },
      "score": {
        "away": 7,
        "home": 20
      },
      "state": {
        "down": 2,
        "offense": "away",
        "time": 2375,
        "yards to first down": 7,
        "yards to goal": 26
      }
    },
    {
      "number": 109,
      "play": {
        "type": "incomplete pass"
      },
      "score": {
        "away": 7,
        "home": 20
      },
      "state": {
        "down": 1,
        "offense": "away",
        "time": 2418,
        "yards to first down": 10,
        "yards to goal": 17
      },
      "turnovers": [
        {
          "by": "away",
          "recovered": "home",
          "type": "interception"
        }
      ]
    },
    {
      "number": 110,
      "play": {
        "type": "run"
      },
      "score": {
        "away": 7,
        "home": 20
      },
      "state": {
        "down": 1,
        "offense": "home",
        "time": 2425,
        "yards to first down": 10,
        "yards to goal": 91
      }
    },
    {
      "number": 111,
      "play": {
        "type": "incomplete pass"
      },
      "score": {
        "away": 7,
        "home": 20
      },
      "state": {
        "down": 2,
        "offense": "home",
        "time": 2468,
        "yards to first down": 11,
        "yards to goal": 92
      }
    },
    {
      "number": 112,
      "play": {
        "type": "incomplete pass"
      },
      "score": {
        "away": 7,
        "home": 20
      },
      "state": {
        "down": 3,
        "offense": "home",
        "time": 2472,
        "yards to first down": 11,
        "yards to goal": 92
      }
    },
    {
      "number": 113,
      "play": {
        "type": "punt"
      },
      "score": {
        "away": 7,
        "home": 20
      },
      "state": {
        "down": 4,
        "offense": "home",
        "time": 2476,
        "yards to first down": 11,
        "yards to goal": 92
      }
    },
    {
      "number": 114,
      "play": {
        "type": "run"
      },
      "score": {
        "away": 7,
        "home": 20
      },
      "state": {
        "down": 1,
        "offense": "away",
        "time": 2484,
        "yards to first down": 10,
        "yards to goal": 64
      }
    },
    {
      "number": 115,
      "play": {
        "type": "incomplete pass"
      },
      "score": {
        "away": 7,
        "home": 20
      },
      "state": {
        "down": 2,
        "offense": "away",
        "time": 2518,
        "yards to first down": 5,
        "yards to goal": 59
      }
    },
    {
      "number": 116,
      "play": {
        "type": "complete pass"
      },
      "score": {
        "away": 7,
        "home": 20
      },
      "state": {
        "down": 3,
        "offense": "away",
        "time": 2523,
        "yards to first down": 5,
        "yards to goal": 59
      }
    },
    {
      "number": 117,
      "play": {
        "type": "run"
      },
      "score": {
        "away": 7,
        "home": 20
      },
      "state": {
        "down": 1,
        "offense": "away",
        "time": 2559,
        "yards to first down": 10,
        "yards to goal": 50
      }
    },
    {
      "number": 118,
      "play": {
        "type": "run"
      },
      "score": {
        "away": 7,
        "home": 20
      },
      "state": {
        "down": 2,
        "offense": "away",
        "time": 2591,
        "yards to first down": 4,
        "yards to goal": 44
      }
    },
    {
      "number": 119,
      "play": {
        "type": "complete pass"
      },
      "score": {
        "away": 7,
        "home": 20
      },
      "state": {
        "down": 3,
        "offense": "away",
        "time": 2635,
        "yards to first down": 2,
        "yards to goal": 42
      }
    },
    {
      "number": 120,
      "play": {
        "type": "complete pass"
      },
      "score": {
        "away": 7,
        "home": 20
      },
      "state": {
        "down": 1,
        "offense": "away",
        "time": 2677,
        "yards to first down": 10,
        "yards to goal": 31
      }
    },
    {
      "number": 121,
      "penalty": {
        "no play": true,
        "penalties": [
          {
            "accepted": true,
            "name": "Defensive Pass Interference",
            "offender": "Sergio Brown",
            "team": "home",
            "yards": 20
          }
        ]
      },
      "play": {
        "type": "incomplete pass"
      },
      "score": {
        "away": 7,
        "home": 20
      },
      "state": {
        "down": 2,
        "offense": "away",
        "time": 2700,
        "yards to first down": 3,
        "yards to goal": 24
      }
    },
    {
      "number": 122,
      "play": {
        "type": "run"
      },
      "score": {
        "away": 7,
        "home": 20
      },
      "state": {
        "down": 1,
        "offense": "away",
        "time": 2705,
        "yards to first down": 4,
        "yards to goal": 4
      }
    },
    {
      "number": 123,
      "play": {
        "type": "sack"
      },
      "score": {
        "away": 7,
        "home": 20
      },
      "state": {
        "down": 2,
        "offense": "away",
        "time": 2747,
        "yards to first down": 3,
        "yards to goal": 3
      }
    },
    {
      "number": 124,
      "play": {
        "scoring": {
          "team": "away",
          "type": "touchdown"
        },
        "type": "complete pass"
      },
      "score": {
        "away": 13,
        "home": 20
      },
      "state": {
        "down": 3,
        "offense": "away",
        "time": 2781,
        "yards to first down": 3,
        "yards to goal": 3
      }
    },
    {
      "number": 125,
      "play": {
        "scoring": {
          "team": "away",
          "type": "extra point"
        },
        "type": "extra point"
      },
      "score": {
        "away": 14,
        "home": 20
      },
      "state": {
        "offense": "away",
        "time": 2781,
        "yards to goal": 2
      }
    },
    {
      "number": 126,
      "play": {
        "type": "kick off"
      },
      "score": {
        "away": 14,
        "home": 20
      },
      "state": {
        "offense": "home",
        "time": 2781,
        "yards to goal": 35
      }
    },
    {
      "number": 127,
      "play": {
        "type": "run"
      },
      "score": {
        "away": 14,
        "home": 20
      },
      "state": {
        "down": 1,
        "offense": "home",
        "time": 2787,
        "yards to first down": 10,
        "yards to goal": 80
      }
    },
    {
      "number": 128,
      "play": {
        "type": "complete pass"
      },
      "score": {
        "away": 14,
        "home": 20
      },
      "state": {
        "down": 1,
        "offense": "home",
        "time": 2812,
        "yards to first down": 10,
        "yards to goal": 69
      }
    },
    {
      "number": 129,
      "play": {
        "type": "complete pass"
      },
      "score": {
        "away": 14,
        "home": 20
      },
      "state": {
        "down": 1,
        "offense": "home",
        "time": 2841,
        "yards to first down": 10,
        "yards to goal": 55
      }
    },
    {
      "number": 130,
      "penalty": {
        "no play": true,
        "penalties": [
          {
            "accepted": true,
            "name": "Offensive Holding",
            "offender": "Matt Light",
            "team": "home",
            "yards": 10
          }
        ]
      },
      "play": {
        "type": "incomplete pass"
      },
      "score": {
        "away": 14,
        "home": 20
      },
      "state": {
        "down": 2,
        "offense": "home",
        "time": 2864,
        "yards to first down": 5,
        "yards to goal": 50
      }
    },
    {
      "number": 131,
      "play": {
        "type": "complete pass"
      },
      "score": {
        "away": 14,
        "home": 20
      },
      "state": {
        "down": 2,
        "offense": "home",
        "time": 2873,
        "yards to first down": 15,
        "yards to goal": 60
      }
    },
    {
      "number": 132,
      "play": {
        "type": "incomplete pass"
      },
      "score": {
        "away": 14,
        "home": 20
      },
      "state": {
        "down": 3,
        "offense": "home",
        "time": 2894,
        "yards to first down": 4,
        "yards to goal": 49
      }
    },
    {
      "number": 133,
      "play": {
        "type": "incomplete pass"
      },
      "score": {
        "away": 14,
        "home": 20
      },
      "state": {
        "down": 4,
        "offense": "home",
        "time": 2895,
        "yards to first down": 4,
        "yards to goal": 49
      }
    },
    {
      "number": 134,
      "play": {
        "type": "complete pass"
      },
      "score": {
        "away": 14,
        "home": 20
      },
      "state": {
        "down": 1,
        "offense": "away",
        "time": 2899,
        "yards to first down": 10,
        "yards to goal": 51
      }
    },
    {
      "number": 135,
      "play": {
        "type": "complete pass"
      },
      "score": {
        "away": 14,
        "home": 20
      },
      "state": {
        "down": 1,
        "offense": "away",
        "time": 2935,
        "yards to first down": 10,
        "yards to goal": 39
      }
    },
    {
      "number": 136,
      "play": {
        "type": "run"
      },
      "score": {
        "away": 14,
        "home": 20
      },
      "state": {
        "down": 2,
        "offense": "away",
        "time": 2973,
        "yards to first down": 5,
        "yards to goal": 34
      },
      "turnovers": [
        {
          "by": "away",
          "recovered": "home",
          "type": "fumble"
        }
      ]
    },
    {
      "number": 137,
      "play": {
        "type": "run"
      },
      "score": {
        "away": 14,
        "home": 20
      },
      "state": {
        "down": 1,
        "offense": "home",
        "time": 2980,
        "yards to first down": 10,
        "yards to goal": 61
      }
    },
    {
      "number": 138,
      "play": {
        "type": "complete pass"
      },
      "score": {
        "away": 14,
        "home": 20
      },
      "state": {
        "down": 2,
        "offense": "home",
        "time": 3013,
        "yards to first down": 11,
        "yards to goal": 62
      }
    },
    {
      "number": 139,
      "play": {
        "type": "complete pass"
      },
      "score": {
        "away": 14,
        "home": 20
      },
      "state": {
        "down": 1,
        "offense": "home",
        "time": 3033,
        "yards to first down": 10,
        "yards to goal": 29
      }
    },
    {
      "number": 140,
      "play": {
        "scoring": {
          "team": "home",
          "type": "touchdown"
        },
        "type": "complete pass"
      },
      "score": {
        "away": 14,
        "home": 26
      },
      "state": {
        "down": 1,
        "offense": "home",
        "time": 3076,
        "yards to first down": 10,
        "yards to goal": 17
      }
    },
    {
      "number": 141,
      "play": {
        "scoring": {
          "team": "home",
          "type": "two point conversion"
        },
        "type": "two point conversion with run"
      },
      "score": {
        "away": 14,
        "home": 28
      },
      "state": {
        "offense": "home",
        "time": 3076
      }
    },
    {
      "number": 142,
      "play": {
        "type": "kick off"
      },
      "score": {
        "away": 14,
        "home": 28
      },
      "state": {
        "offense": "away",
        "time": 3076,
        "yards to goal": 35
      }
    },
    {
      "number": 143,
      "play": {
        "type": "complete pass"
      },
      "score": {
        "away": 14,
        "home": 28
      },
      "state": {
        "down": 1,
        "offense": "away",
        "time": 3080,
        "yards to first down": 10,
        "yards to goal": 80
      }
    },
    {
      "number": 144,
      "play": {
        "type": "complete pass"
      },
      "score": {
        "away": 14,
        "home": 28
      },
      "state": {
        "down": 2,
        "offense": "away",
        "time": 3113,
        "yards to first down": 4,
        "yards to goal": 74
      }
    },
    {
      "number": 145,
      "play": {
        "type": "incomplete pass"
      },
      "score": {
        "away": 14,
        "home": 28
      },
      "state": {
        "down": 1,
        "offense": "away",
        "time": 3143,
        "yards to first down": 10,
        "yards to goal": 69
      }
    },
    {
      "number": 146,
      "play": {
        "type": "incomplete pass"
      },
      "score": {
        "away": 14,
        "home": 28
      },
      "state": {
        "down": 2,
        "offense": "away",
        "time": 3149,
        "yards to first down": 10,
        "yards to goal": 69
      }
    },
    {
      "number": 147,
      "play": {
        "type": "complete pass"
      },
      "score": {
        "away": 14,
        "home": 28
      },
      "state": {
        "down": 3,
        "offense": "away",
        "time": 3155,
        "yards to first down": 10,
        "yards to goal": 69
      }
    },
    {
      "number": 148,
      "play": {
        "type": "complete pass"
      },
      "score": {
        "away": 14,
        "home": 28
      },
      "state": {
        "down": 1,
        "offense": "away",
        "time": 3189,
        "yards to first down": 10,
        "yards to goal": 55
      }
    },
    {
      "number": 149,
      "play": {
        "type": "run"
      },
      "score": {
        "away": 14,
        "home": 28
      },
      "state": {
        "down": 1,
        "offense": "away",
        "time": 3221,
        "yards to first down": 10,
        "yards to goal": 37
      }
    },
    {
      "number": 150,
      "play": {
        "scoring": {
          "team": "away",
          "type": "touchdown"
        },
        "type": "complete pass"
      },
      "score": {
        "away": 20,
        "home": 28
      },
      "state": {
        "down": 1,
        "offense": "away",
        "time": 3253,
        "yards to first down": 10,
        "yards to goal": 26
      }
    },
    {
      "number": 151,
      "play": {
        "scoring": {
          "team": "away",
          "type": "extra point"
        },
        "type": "extra point"
      },
      "score": {
        "away": 21,
        "home": 28
      },
      "state": {
        "offense": "away",
        "time": 3253
      }
    },
    {
      "number": 152,
      "play": {
        "type": "kick off"
      },
      "score": {
        "away": 21,
        "home": 28
      },
      "state": {
        "offense": "home",
        "time": 3253,
        "yards to goal": 35
      }
    },
    {
      "number": 153,
      "play": {
        "type": "run"
      },
      "score": {
        "away": 21,
        "home": 28
      },
      "state": {
        "down": 1,
        "offense": "home",
        "time": 3260,
        "yards to first down": 10,
        "yards to goal": 80
      }
    },
    {
      "number": 154,
      "penalty": {
        "no play": false,
        "penalties": [
          {
            "accepted": false,
            "name": "Defensive Holding",
            "offender": "Antoine Cason",
            "team": "away"
          }
        ]
      },
      "play": {
        "type": "complete pass"
      },
      "score": {
        "away": 21,
        "home": 28
      },
      "state": {
        "down": 2,
        "offense": "home",
        "time": 3302,
        "yards to first down": 7,
        "yards to goal": 77
      }
    },
    {
      "number": 155,
      "play": {
        "type": "run"
      },
      "score": {
        "away": 21,
        "home": 28
      },
      "state": {
        "down": 1,
        "offense": "home",
        "time": 3309,
        "yards to first down": 10,
        "yards to goal": 64
      }
    },
    {
      "number": 156,
      "play": {
        "type": "run"
      },
      "score": {
        "away": 21,
        "home": 28
      },
      "state": {
        "down": 2,
        "offense": "home",
        "time": 3353,
        "yards to first down": 5,
        "yards to goal": 59
      }
    },
    {
      "number": 157,
      "play": {
        "type": "run"
      },
      "score": {
        "away": 21,
        "home": 28
      },
      "state": {
        "down": 3,
        "offense": "home",
        "time": 3398,
        "yards to first down": 1,
        "yards to goal": 55
      }
    },
    {
      "number": 158,
      "play": {
        "type": "incomplete pass"
      },
      "score": {
        "away": 21,
        "home": 28
      },
      "state": {
        "down": 1,
        "offense": "home",
        "time": 3443,
        "yards to first down": 10,
        "yards to goal": 53
      }
    },
    {
      "number": 159,
      "play": {
        "type": "complete pass"
      },
      "score": {
        "away": 21,
        "home": 28
      },
      "state": {
        "down": 2,
        "offense": "home",
        "time": 3446,
        "yards to first down": 10,
        "yards to goal": 53
      }
    },
    {
      "number": 160,
      "play": {
        "type": "timeout"
      },
      "score": {
        "away": 21,
        "home": 28
      },
      "state": {
        "offense": "home",
        "time": 3461
      }
    },
    {
      "number": 161,
      "play": {
        "type": "run"
      },
      "score": {
        "away": 21,
        "home": 28
      },
      "state": {
        "down": 1,
        "offense": "home",
        "time": 3461,
        "yards to first down": 10,
        "yards to goal": 24
      }
    },
    {
      "number": 162,
      "penalty": {
        "no play": true,
        "penalties": [
          {
            "accepted": true,
            "name": "Neutral Zone Infraction",
            "offender": "Cam Thomas",
            "team": "away",
            "yards": 5
          }
        ]
      },
      "play": {
        "type": "penalty"
      },
      "score": {
        "away": 21,
        "home": 28
      },
      "state": {
        "down": 2,
        "offense": "home",
        "time": 3480,
        "yards to first down": 7,
        "yards to goal": 21
      }
    },
    {
      "number": 163,
      "play": {
        "scoring": {
          "team": "home",
          "type": "touchdown"
        },
        "type": "run"
      },
      "score": {
        "away": 21,
        "home": 34
      },
      "state": {
        "down": 2,
        "offense": "home",
        "time": 3480,
        "yards to first down": 2,
        "yards to goal": 16
      }
    },
    {
      "number": 164,
      "play": {
        "scoring": {
          "team": "home",
          "type": "extra point"
        },
        "type": "extra point"
      },
      "score": {
        "away": 21,
        "home": 35
      },
      "state": {
        "offense": "home",
        "time": 3480
      }
    },
    {
      "number": 165,
      "play": {
        "type": "kick off"
      },
      "score": {
        "away": 21,
        "home": 35
      },
      "state": {
        "offense": "away",
        "time": 3480,
        "yards to goal": 35
      }
    },
    {
      "number": 166,
      "play": {
        "type": "complete pass"
      },
      "score": {
        "away": 21,
        "home": 35
      },
      "state": {
        "down": 1,
        "offense": "away",
        "time": 3491,
        "yards to first down": 10,
        "yards to goal": 87
      }
    },
    {
      "number": 167,
      "play": {
        "type": "timeout"
      },
      "score": {
        "away": 21,
        "home": 35
      },
      "state": {
        "offense": "away",
        "time": 3498
      }
    },
    {
      "number": 168,
      "play": {
        "type": "complete pass"
      },
      "score": {
        "away": 21,
        "home": 35
      },
      "state": {
        "down": 1,
        "offense": "away",
        "time": 3498,
        "yards to first down": 10,
        "yards to goal": 76
      }
    },
    {
      "number": 169,
      "play": {
        "type": "sack"
      },
      "score": {
        "away": 21,
        "home": 35
      },
      "state": {
        "down": 1,
        "offense": "away",
        "time": 3531,
        "yards to first down": 10,
        "yards to goal": 62
      },
      "turnovers": [
        {
          "by": "away",
          "recovered": "home",
          "type": "fumble"
        }
      ]
    },
    {
      "number": 170,
      "play": {
        "type": "run"
      },
      "score": {
        "away": 21,
        "home": 35
      },
      "state": {
        "down": 1,
        "offense": "home",
        "time": 3538,
        "yards to first down": 10,
        "yards to goal": 32
      }
    },
    {
      "number": 171,
      "play": {
        "type": "kneel"
      },
      "score": {
        "away": 21,
        "home": 35
      },
      "state": {
        "down": 2,
        "offense": "home",
        "time": 3583,
        "yards to first down": 8,
        "yards to goal": 30
      }
    }
  ],
  "team stats": {
    "away": {
      "first downs": 29,
      "fumbles": {
        "lost": 2,
        "plays": 2
      },
      "pass": {
        "interceptions": 2,
        "plays": 40,
        "successful": 29,
        "touchdowns": 2,
        "yards": 378
      },
      "penalties": {
        "plays": 6,
        "yards": -44
      },
      "rush": {
        "plays": 24,
        "touchdowns": 1,
        "yards": 98
      },
      "sacks": {
        "plays": 2,
        "yards": -6
      }
    },
    "home": {
      "first downs": 28,
      "fumbles": {
        "lost": 0,
        "plays": 0
      },
      "pass": {
        "interceptions": 0,
        "plays": 40,
        "successful": 31,
        "touchdowns": 3,
        "yards": 423
      },
      "penalties": {
        "plays": 8,
        "yards": -80
      },
      "rush": {
        "plays": 25,
        "touchdowns": 1,
        "yards": 94
      },
      "sacks": {
        "plays": 2,
        "yards": -13
      }
    }
  },
  "venue": {
    "attendance": 68756,
    "dome": false,
    "stadium": "Gillette Stadium",
    "surface": "fieldturf"
  }
}