{
  "_version": {
    "parser": "f1b43e60dfa71b57a38898e9a33c06ee432a8c2b",
    "raw": "397ae73f37cccc39e678f289840992fa70024208"
  },
  "away team": "PIT",
  "betting": {
    "over under": 44.0,
    "spread": -3.0,
    "winner": "away"
  },
  "datetime": {
    "date": "2002-12-01",
    "start time": "13:00"
  },
  "home team": "JAC",
  "officials": {
    "back judge": "Jim Howey",
    "field judge": "Scott Edwards",
    "head linesman": "John Schleyer",
    "line judge": "Carl Johnson",
    "referee": "Gerald Austin",
    "side judge": "Rick Patterson",
    "umpire": "Tony Michalek"
  },
  "players": {
    "away": {},
    "home": {}
  },
  "plays": [
    {
      "number": 0,
      "play": {
        "type": "kick off"
      },
      "score": {
        "away": 0,
        "home": 0
      },
      "state": {
        "offense": "away",
        "time": 0,
        "yards to goal": 30
      }
    },
    {
      "number": 1,
      "play": {
        "type": "complete pass"
      },
      "score": {
        "away": 0,
        "home": 0
      },
      "state": {
        "down": 1,
        "offense": "away",
        "time": 4,
        "yards to first down": 10,
        "yards to goal": 68
      }
    },
    {
      "number": 2,
      "play": {
        "type": "complete pass"
      },
      "score": {
        "away": 0,
        "home": 0
      },
      "state": {
        "down": 2,
        "offense": "away",
        "time": 36,
        "yards to first down": 6,
        "yards to goal": 64
      }
    },
    {
      "number": 3,
      "play": {
        "type": "run"
      },
      "score": {
        "away": 0,
        "home": 0
      },
      "state": {
        "down": 1,
        "offense": "away",
        "time": 81,
        "yards to first down": 10,
        "yards to goal": 10
      }
    },
    {
      "number": 4,
      "play": {
        "type": "incomplete pass"
      },
      "score": {
        "away": 0,
        "home": 0
      },
      "state": {
        "down": 2,
        "offense": "away",
        "time": 123,
        "yards to first down": 7,
        "yards to goal": 7
      }
    },
    {
      "number": 5,
      "play": {
        "type": "incomplete pass"
      },
      "score": {
        "away": 0,
        "home": 0
      },
      "state": {
        "down": 3,
        "offense": "away",
        "time": 128,
        "yards to first down": 7,
        "yards to goal": 7
      }
    },
    {
      "number": 6,
      "play": {
        "scoring": {
          "team": "away",
          "type": "field goal"
        },
        "type": "field goal"
      },
      "score": {
        "away": 3,
        "home": 0
      },
      "state": {
        "down": 4,
        "offense": "away",
        "time": 133,
        "yards to first down": 7,
        "yards to goal": 7
      }
    },
    {
      "number": 7,
      "play": {
        "type": "kick off"
      },
      "score": {
        "away": 3,
        "home": 0
      },
      "state": {
        "offense": "home",
        "time": 133,
        "yards to goal": 30
      }
    },
    {
      "number": 8,
      "play": {
        "type": "run"
      },
      "score": {
        "away": 3,
        "home": 0
      },
      "state": {
        "down": 1,
        "offense": "home",
        "time": 143,
        "yards to first down": 10,
        "yards to goal": 80
      }
    },
    {
      "number": 9,
      "play": {
        "type": "incomplete pass"
      },
      "score": {
        "away": 3,
        "home": 0
      },
      "state": {
        "down": 2,
        "offense": "home",
        "time": 180,
        "yards to first down": 7,
        "yards to goal": 77
      }
    },
    {
      "number": 10,
      "play": {
        "type": "incomplete pass"
      },
      "score": {
        "away": 3,
        "home": 0
      },
      "state": {
        "down": 3,
        "offense": "home",
        "time": 184,
        "yards to first down": 7,
        "yards to goal": 77
      }
    },
    {
      "number": 11,
      "play": {
        "type": "punt"
      },
      "score": {
        "away": 3,
        "home": 0
      },
      "state": {
        "down": 4,
        "offense": "home",
        "time": 190,
        "yards to first down": 7,
        "yards to goal": 77
      }
    },
    {
      "number": 12,
      "play": {
        "type": "complete pass"
      },
      "score": {
        "away": 3,
        "home": 0
      },
      "state": {
        "down": 1,
        "offense": "away",
        "time": 198,
        "yards to first down": 10,
        "yards to goal": 66
      }
    },
    {
      "number": 13,
      "play": {
        "type": "run"
      },
      "score": {
        "away": 3,
        "home": 0
      },
      "state": {
        "down": 2,
        "offense": "away",
        "time": 234,
        "yards to first down": 4,
        "yards to goal": 60
      }
    },
    {
      "number": 14,
      "play": {
        "type": "complete pass"
      },
      "score": {
        "away": 3,
        "home": 0
      },
      "state": {
        "down": 1,
        "offense": "away",
        "time": 275,
        "yards to first down": 10,
        "yards to goal": 54
      }
    },
    {
      "number": 15,
      "play": {
        "type": "complete pass"
      },
      "score": {
        "away": 3,
        "home": 0
      },
      "state": {
        "down": 2,
        "offense": "away",
        "time": 316,
        "yards to first down": 5,
        "yards to goal": 49
      }
    },
    {
      "number": 16,
      "play": {
        "type": "run"
      },
      "score": {
        "away": 3,
        "home": 0
      },
      "state": {
        "down": 1,
        "offense": "away",
        "time": 357,
        "yards to first down": 10,
        "yards to goal": 38
      }
    },
    {
      "number": 17,
      "play": {
        "type": "run"
      },
      "score": {
        "away": 3,
        "home": 0
      },
      "state": {
        "down": 2,
        "offense": "away",
        "time": 394,
        "yards to first down": 6,
        "yards to goal": 34
      }
    },
    {
      "number": 18,
      "play": {
        "type": "run"
      },
      "score": {
        "away": 3,
        "home": 0
      },
      "state": {
        "down": 1,
        "offense": "away",
        "time": 436,
        "yards to first down": 10,
        "yards to goal": 26
      }
    },
    {
      "number": 19,
      "play": {
        "type": "complete pass"
      },
      "score": {
        "away": 3,
        "home": 0
      },
      "state": {
        "down": 2,
        "offense": "away",
        "time": 484,
        "yards to first down": 6,
        "yards to goal": 22
      }
    },
    {
      "number": 20,
      "play": {
        "type": "timeout"
      },
      "score": {
        "away": 3,
        "home": 0
      },
      "state": {
        "offense": "away",
        "time": 529
      }
    },
    {
      "number": 21,
      "play": {
        "type": "run"
      },
      "score": {
        "away": 3,
        "home": 0
      },
      "state": {
        "down": 1,
        "offense": "away",
        "time": 529,
        "yards to first down": 10,
        "yards to goal": 15
      }
    },
    {
      "number": 22,
      "play": {
        "type": "incomplete pass"
      },
      "score": {
        "away": 3,
        "home": 0
      },
      "state": {
        "down": 2,
        "offense": "away",
        "time": 570,
        "yards to first down": 6,
        "yards to goal": 11
      }
    },
    {
      "number": 23,
      "play": {
        "type": "incomplete pass"
      },
      "score": {
        "away": 3,
        "home": 0
      },
      "state": {
        "down": 3,
        "offense": "away",
        "time": 574,
        "yards to first down": 6,
        "yards to goal": 11
      }
    },
    {
      "number": 24,
      "play": {
        "scoring": {
          "team": "away",
          "type": "field goal"
        },
        "type": "field goal"
      },
      "score": {
        "away": 6,
        "home": 0
      },
      "state": {
        "down": 4,
        "offense": "away",
        "time": 578,
        "yards to first down": 6,
        "yards to goal": 11
      }
    },
    {
      "number": 25,
      "play": {
        "type": "kick off"
      },
      "score": {
        "away": 6,
        "home": 0
      },
      "state": {
        "offense": "home",
        "time": 578,
        "yards to goal": 30
      }
    },
    {
      "number": 26,
      "play": {
        "type": "run"
      },
      "score": {
        "away": 6,
        "home": 0
      },
      "state": {
        "down": 1,
        "offense": "home",
        "time": 591,
        "yards to first down": 10,
        "yards to goal": 46
      }
    },
    {
      "number": 27,
      "play": {
        "type": "run"
      },
      "score": {
        "away": 6,
        "home": 0
      },
      "state": {
        "down": 2,
        "offense": "home",
        "time": 628,
        "yards to first down": 6,
        "yards to goal": 42
      }
    },
    {
      "number": 28,
      "play": {
        "type": "complete pass"
      },
      "score": {
        "away": 6,
        "home": 0
      },
      "state": {
        "down": 3,
        "offense": "home",
        "time": 666,
        "yards to first down": 3,
        "yards to goal": 39
      }
    },
    {
      "number": 29,
      "play": {
        "type": "run"
      },
      "score": {
        "away": 6,
        "home": 0
      },
      "state": {
        "down": 1,
        "offense": "home",
        "time": 705,
        "yards to first down": 10,
        "yards to goal": 27
      }
    },
    {
      "number": 30,
      "play": {
        "scoring": {
          "team": "home",
          "type": "touchdown"
        },
        "type": "run"
      },
      "score": {
        "away": 6,
        "home": 6
      },
      "state": {
        "down": 2,
        "offense": "home",
        "time": 746,
        "yards to first down": 1,
        "yards to goal": 18
      }
    },
    {
      "number": 31,
      "play": {
        "scoring": {
          "team": "home",
          "type": "extra point"
        },
        "type": "extra point"
      },
      "score": {
        "away": 6,
        "home": 7
      },
      "state": {
        "offense": "home",
        "time": 746
      }
    },
    {
      "number": 32,
      "play": {
        "type": "kick off"
      },
      "score": {
        "away": 6,
        "home": 7
      },
      "state": {
        "offense": "away",
        "time": 746,
        "yards to goal": 30
      }
    },
    {
      "number": 33,
      "play": {
        "type": "run"
      },
      "score": {
        "away": 6,
        "home": 7
      },
      "state": {
        "down": 1,
        "offense": "away",
        "time": 758,
        "yards to first down": 10,
        "yards to goal": 71
      }
    },
    {
      "number": 34,
      "play": {
        "type": "run"
      },
      "score": {
        "away": 6,
        "home": 7
      },
      "state": {
        "down": 2,
        "offense": "away",
        "time": 790,
        "yards to first down": 7,
        "yards to goal": 68
      }
    },
    {
      "number": 35,
      "play": {
        "type": "incomplete pass"
      },
      "score": {
        "away": 6,
        "home": 7
      },
      "state": {
        "down": 1,
        "offense": "away",
        "time": 823,
        "yards to first down": 10,
        "yards to goal": 61
      }
    },
    {
      "number": 36,
      "play": {
        "type": "run"
      },
      "score": {
        "away": 6,
        "home": 7
      },
      "state": {
        "down": 2,
        "offense": "away",
        "time": 829,
        "yards to first down": 10,
        "yards to goal": 61
      }
    },
    {
      "number": 37,
      "play": {
        "type": "run"
      },
      "score": {
        "away": 6,
        "home": 7
      },
      "state": {
        "down": 3,
        "offense": "away",
        "time": 869,
        "yards to first down": 3,
        "yards to goal": 54
      }
    },
    {
      "number": 38,
      "play": {
        "type": "run"
      },
      "score": {
        "away": 6,
        "home": 7
      },
      "state": {
        "down": 1,
        "offense": "away",
        "time": 900,
        "yards to first down": 10,
        "yards to goal": 49
      }
    },
    {
      "number": 39,
      "play": {
        "type": "complete pass"
      },
      "score": {
        "away": 6,
        "home": 7
      },
      "state": {
        "down": 2,
        "offense": "away",
        "time": 941,
        "yards to first down": 12,
        "yards to goal": 51
      }
    },
    {
      "number": 40,
      "play": {
        "type": "run"
      },
      "score": {
        "away": 6,
        "home": 7
      },
      "state": {
        "down": 1,
        "offense": "away",
        "time": 986,
        "yards to first down": 10,
        "yards to goal": 39
      }
    },
    {
      "number": 41,
      "play": {
        "scoring": {
          "team": "away",
          "type": "touchdown"
        },
        "type": "run"
      },
      "score": {
        "away": 12,
        "home": 7
      },
      "state": {
        "down": 1,
        "offense": "away",
        "time": 1028,
        "yards to first down": 10,
        "yards to goal": 28
      }
    },
    {
      "number": 42,
      "play": {
        "scoring": {
          "team": "away",
          "type": "extra point"
        },
        "type": "extra point"
      },
      "score": {
        "away": 13,
        "home": 7
      },
      "state": {
        "offense": "away",
        "time": 1028
      }
    },
    {
      "number": 43,
      "play": {
        "type": "kick off"
      },
      "score": {
        "away": 13,
        "home": 7
      },
      "state": {
        "offense": "home",
        "time": 1028,
        "yards to goal": 30
      }
    },
    {
      "number": 44,
      "play": {
        "type": "run"
      },
      "score": {
        "away": 13,
        "home": 7
      },
      "state": {
        "down": 1,
        "offense": "home",
        "time": 1042,
        "yards to first down": 10,
        "yards to goal": 68
      }
    },
    {
      "number": 45,
      "play": {
        "type": "run"
      },
      "score": {
        "away": 13,
        "home": 7
      },
      "state": {
        "down": 2,
        "offense": "home",
        "time": 1067,
        "yards to first down": 13,
        "yards to goal": 71
      }
    },
    {
      "number": 46,
      "play": {
        "type": "complete pass"
      },
      "score": {
        "away": 13,
        "home": 7
      },
      "state": {
        "down": 3,
        "offense": "home",
        "time": 1112,
        "yards to first down": 11,
        "yards to goal": 69
      }
    },
    {
      "number": 47,
      "play": {
        "type": "punt"
      },
      "score": {
        "away": 13,
        "home": 7
      },
      "state": {
        "down": 4,
        "offense": "home",
        "time": 1143,
        "yards to first down": 4,
        "yards to goal": 62
      }
    },
    {
      "number": 48,
      "play": {
        "type": "run"
      },
      "score": {
        "away": 13,
        "home": 7
      },
      "state": {
        "down": 1,
        "offense": "away",
        "time": 1150,
        "yards to first down": 10,
        "yards to goal": 63
      }
    },
    {
      "number": 49,
      "play": {
        "type": "run"
      },
      "score": {
        "away": 13,
        "home": 7
      },
      "state": {
        "down": 1,
        "offense": "away",
        "time": 1180,
        "yards to first down": 10,
        "yards to goal": 48
      }
    },
    {
      "number": 50,
      "play": {
        "type": "complete pass"
      },
      "score": {
        "away": 13,
        "home": 7
      },
      "state": {
        "down": 2,
        "offense": "away",
        "time": 1219,
        "yards to first down": 11,
        "yards to goal": 49
      }
    },
    {
      "number": 51,
      "play": {
        "type": "complete pass"
      },
      "score": {
        "away": 13,
        "home": 7
      },
      "state": {
        "down": 3,
        "offense": "away",
        "time": 1262,
        "yards to first down": 2,
        "yards to goal": 40
      }
    },
    {
      "number": 52,
      "play": {
        "type": "run"
      },
      "score": {
        "away": 13,
        "home": 7
      },
      "state": {
        "down": 4,
        "offense": "away",
        "time": 1299,
        "yards to first down": 3,
        "yards to goal": 41
      }
    },
    {
      "number": 53,
      "play": {
        "type": "incomplete pass"
      },
      "score": {
        "away": 13,
        "home": 7
      },
      "state": {
        "down": 1,
        "offense": "away",
        "time": 1345,
        "yards to first down": 10,
        "yards to goal": 25
      },
      "turnovers": [
        {
          "by": "away",
          "recovered": "home",
          "type": "interception"
        }
      ]
    },
    {
      "number": 54,
      "play": {
        "type": "complete pass"
      },
      "score": {
        "away": 13,
        "home": 7
      },
      "state": {
        "down": 1,
        "offense": "home",
        "time": 1360,
        "yards to first down": 10,
        "yards to goal": 27
      }
    },
    {
      "number": 55,
      "play": {
        "type": "run"
      },
      "score": {
        "away": 13,
        "home": 7
      },
      "state": {
        "down": 1,
        "offense": "home",
        "time": 1404,
        "yards to first down": 10,
        "yards to goal": 10
      }
    },
    {
      "number": 56,
      "play": {
        "type": "run"
      },
      "score": {
        "away": 13,
        "home": 7
      },
      "state": {
        "down": 2,
        "offense": "home",
        "time": 1438,
        "yards to first down": 7,
        "yards to goal": 7
      }
    },
    {
      "number": 57,
      "play": {
        "type": "sack"
      },
      "score": {
        "away": 13,
        "home": 7
      },
      "state": {
        "down": 3,
        "offense": "home",
        "time": 1483,
        "yards to first down": 5,
        "yards to goal": 5
      }
    },
    {
      "number": 58,
      "play": {
        "scoring": {
          "team": "home",
          "type": "field goal"
        },
        "type": "field goal"
      },
      "score": {
        "away": 13,
        "home": 10
      },
      "state": {
        "down": 4,
        "offense": "home",
        "time": 1525,
        "yards to first down": 5,
        "yards to goal": 5
      }
    },
    {
      "number": 59,
      "play": {
        "type": "kick off"
      },
      "score": {
        "away": 13,
        "home": 10
      },
      "state": {
        "offense": "away",
        "time": 1525,
        "yards to goal": 30
      }
    },
    {
      "number": 60,
      "play": {
        "type": "run"
      },
      "score": {
        "away": 13,
        "home": 10
      },
      "state": {
        "down": 1,
        "offense": "away",
        "time": 1534,
        "yards to first down": 10,
        "yards to goal": 56
      }
    },
    {
      "number": 61,
      "play": {
        "type": "run"
      },
      "score": {
        "away": 13,
        "home": 10
      },
      "state": {
        "down": 1,
        "offense": "away",
        "time": 1574,
        "yards to first down": 10,
        "yards to goal": 43
      }
    },
    {
      "number": 62,
      "play": {
        "type": "run"
      },
      "score": {
        "away": 13,
        "home": 10
      },
      "state": {
        "down": 2,
        "offense": "away",
        "time": 1615,
        "yards to first down": 8,
        "yards to goal": 41
      }
    },
    {
      "number": 63,
      "play": {
        "type": "run"
      },
      "score": {
        "away": 13,
        "home": 10
      },
      "state": {
        "down": 1,
        "offense": "away",
        "time": 1665,
        "yards to first down": 10,
        "yards to goal": 13
      }
    },
    {
      "number": 64,
      "play": {
        "type": "run"
      },
      "score": {
        "away": 13,
        "home": 10
      },
      "state": {
        "down": 2,
        "offense": "away",
        "time": 1680,
        "yards to first down": 9,
        "yards to goal": 12
      }
    },
    {
      "number": 65,
      "play": {
        "type": "timeout"
      },
      "score": {
        "away": 13,
        "home": 10
      },
      "state": {
        "offense": "away",
        "time": 1687
      }
    },
    {
      "number": 66,
      "play": {
        "type": "incomplete pass"
      },
      "score": {
        "away": 13,
        "home": 10
      },
      "state": {
        "down": 3,
        "offense": "away",
        "time": 1687,
        "yards to first down": 8,
        "yards to goal": 11
      }
    },
    {
      "number": 67,
      "play": {
        "scoring": {
          "team": "away",
          "type": "field goal"
        },
        "type": "field goal"
      },
      "score": {
        "away": 16,
        "home": 10
      },
      "state": {
        "down": 4,
        "offense": "away",
        "time": 1694,
        "yards to first down": 8,
        "yards to goal": 11
      }
    },
    {
      "number": 68,
      "play": {
        "type": "kick off"
      },
      "score": {
        "away": 16,
        "home": 10
      },
      "state": {
        "offense": "home",
        "time": 1694,
        "yards to goal": 30
      }
    },
    {
      "number": 69,
      "play": {
        "type": "run"
      },
      "score": {
        "away": 16,
        "home": 10
      },
      "state": {
        "down": 1,
        "offense": "home",
        "time": 1701,
        "yards to first down": 10,
        "yards to goal": 65
      }
    },
    {
      "number": 70,
      "play": {
        "type": "complete pass"
      },
      "score": {
        "away": 16,
        "home": 10
      },
      "state": {
        "down": 2,
        "offense": "home",
        "time": 1708,
        "yards to first down": 4,
        "yards to goal": 59
      }
    },
    {
      "number": 71,
      "play": {
        "type": "complete pass"
      },
      "score": {
        "away": 16,
        "home": 10
      },
      "state": {
        "down": 3,
        "offense": "home",
        "time": 1732,
        "yards to first down": 8,
        "yards to goal": 63
      }
    },
    {
      "number": 72,
      "play": {
        "type": "incomplete pass"
      },
      "score": {
        "away": 16,
        "home": 10
      },
      "state": {
        "down": 1,
        "offense": "home",
        "time": 1745,
        "yards to first down": 10,
        "yards to goal": 44
      }
    },
    {
      "number": 73,
      "play": {
        "type": "run"
      },
      "score": {
        "away": 16,
        "home": 10
      },
      "state": {
        "down": 2,
        "offense": "home",
        "time": 1745,
        "yards to first down": 10,
        "yards to goal": 44
      }
    },
    {
      "number": 74,
      "play": {
        "type": "timeout"
      },
      "score": {
        "away": 16,
        "home": 10
      },
      "state": {
        "offense": "home",
        "time": 1754
      }
    },
    {
      "number": 75,
      "play": {
        "type": "incomplete pass"
      },
      "score": {
        "away": 16,
        "home": 10
      },
      "state": {
        "down": 3,
        "offense": "home",
        "time": 1754,
        "yards to first down": 8,
        "yards to goal": 42
      }
    },
    {
      "number": 76,
      "play": {
        "type": "punt"
      },
      "score": {
        "away": 16,
        "home": 10
      },
      "state": {
        "down": 4,
        "offense": "home",
        "time": 1757,
        "yards to first down": 8,
        "yards to goal": 42
      }
    },
    {
      "number": 77,
      "play": {
        "type": "run"
      },
      "score": {
        "away": 16,
        "home": 10
      },
      "state": {
        "down": 1,
        "offense": "away",
        "time": 1770,
        "yards to first down": 10,
        "yards to goal": 80
      }
    },
    {
      "number": 78,
      "play": {
        "type": "kick off"
      },
      "score": {
        "away": 16,
        "home": 10
      },
      "state": {
        "offense": "home",
        "time": 1770,
        "yards to goal": 30
      }
    },
    {
      "number": 79,
      "play": {
        "type": "run"
      },
      "score": {
        "away": 16,
        "home": 10
      },
      "state": {
        "down": 1,
        "offense": "home",
        "time": 1804,
        "yards to first down": 10,
        "yards to goal": 81
      }
    },
    {
      "number": 80,
      "play": {
        "type": "incomplete pass"
      },
      "score": {
        "away": 16,
        "home": 10
      },
      "state": {
        "down": 2,
        "offense": "home",
        "time": 1840,
        "yards to first down": 5,
        "yards to goal": 76
      }
    },
    {
      "number": 81,
      "penalty": {
        "no play": false,
        "penalties": [
          {
            "accepted": false,
            "name": "Offensive Pass Interference",
            "offender": "Kyle Brady",
            "team": "home"
          }
        ]
      },
      "play": {
        "type": "incomplete pass"
      },
      "score": {
        "away": 16,
        "home": 10
      },
      "state": {
        "down": 3,
        "offense": "home",
        "time": 1844,
        "yards to first down": 5,
        "yards to goal": 76
      }
    },
    {
      "number": 82,
      "play": {
        "type": "punt"
      },
      "score": {
        "away": 16,
        "home": 10
      },
      "state": {
        "down": 4,
        "offense": "home",
        "time": 1850,
        "yards to first down": 5,
        "yards to goal": 76
      }
    },
    {
      "number": 83,
      "play": {
        "type": "complete pass"
      },
      "score": {
        "away": 16,
        "home": 10
      },
      "state": {
        "down": 1,
        "offense": "away",
        "time": 1859,
        "yards to first down": 10,
        "yards to goal": 52
      }
    },
    {
      "number": 84,
      "play": {
        "type": "run"
      },
      "score": {
        "away": 16,
        "home": 10
      },
      "state": {
        "down": 1,
        "offense": "away",
        "time": 1900,
        "yards to first down": 10,
        "yards to goal": 34
      }
    },
    {
      "number": 85,
      "play": {
        "type": "run"
      },
      "score": {
        "away": 16,
        "home": 10
      },
      "state": {
        "down": 2,
        "offense": "away",
        "time": 1941,
        "yards to first down": 7,
        "yards to goal": 31
      }
    },
    {
      "number": 86,
      "play": {
        "type": "run"
      },
      "score": {
        "away": 16,
        "home": 10
      },
      "state": {
        "down": 3,
        "offense": "away",
        "time": 1981,
        "yards to first down": 11,
        "yards to goal": 35
      }
    },
    {
      "number": 87,
      "play": {
        "scoring": {
          "team": "away",
          "type": "field goal"
        },
        "type": "field goal"
      },
      "score": {
        "away": 19,
        "home": 10
      },
      "state": {
        "down": 4,
        "offense": "away",
        "time": 2022,
        "yards to first down": 4,
        "yards to goal": 28
      }
    },
    {
      "number": 88,
      "play": {
        "type": "kick off"
      },
      "score": {
        "away": 19,
        "home": 10
      },
      "state": {
        "offense": "home",
        "time": 2022,
        "yards to goal": 30
      }
    },
    {
      "number": 89,
      "play": {
        "type": "run"
      },
      "score": {
        "away": 19,
        "home": 10
      },
      "state": {
        "down": 1,
        "offense": "home",
        "time": 2035,
        "yards to first down": 10,
        "yards to goal": 75
      }
    },
    {
      "number": 90,
      "penalty": {
        "no play": true,
        "penalties": [
          {
            "accepted": true,
            "name": "Illegal Use of Hands",
            "offender": "Chad Scott",
            "team": "away",
            "yards": 5
          }
        ]
      },
      "play": {
        "type": "incomplete pass"
      },
      "score": {
        "away": 19,
        "home": 10
      },
      "state": {
        "down": 2,
        "offense": "home",
        "time": 2073,
        "yards to first down": 8,
        "yards to goal": 73
      }
    },
    {
      "number": 91,
      "play": {
        "type": "complete pass"
      },
      "score": {
        "away": 19,
        "home": 10
      },
      "state": {
        "down": 1,
        "offense": "home",
        "time": 2082,
        "yards to first down": 10,
        "yards to goal": 68
      }
    },
    {
      "number": 92,
      "play": {
        "type": "run"
      },
      "score": {
        "away": 19,
        "home": 10
      },
      "state": {
        "down": 1,
        "offense": "home",
        "time": 2122,
        "yards to first down": 10,
        "yards to goal": 51
      }
    },
    {
      "number": 93,
      "play": {
        "type": "sack"
      },
      "score": {
        "away": 19,
        "home": 10
      },
      "state": {
        "down": 2,
        "offense": "home",
        "time": 2163,
        "yards to first down": 10,
        "yards to goal": 51
      }
    },
    {
      "number": 94,
      "play": {
        "type": "timeout"
      },
      "score": {
        "away": 19,
        "home": 10
      },
      "state": {
        "offense": "home",
        "time": 2199
      }
    },
    {
      "number": 95,
      "penalty": {
        "no play": false,
        "penalties": [
          {
            "accepted": false,
            "name": "Offensive Pass Interference",
            "offender": "Jimmy Smith",
            "team": "home"
          }
        ]
      },
      "play": {
        "type": "incomplete pass"
      },
      "score": {
        "away": 19,
        "home": 10
      },
      "state": {
        "down": 3,
        "offense": "home",
        "time": 2199,
        "yards to first down": 19,
        "yards to goal": 60
      }
    },
    {
      "number": 96,
      "play": {
        "type": "punt"
      },
      "score": {
        "away": 19,
        "home": 10
      },
      "state": {
        "down": 4,
        "offense": "home",
        "time": 2206,
        "yards to first down": 19,
        "yards to goal": 60
      }
    },
    {
      "number": 97,
      "play": {
        "type": "run"
      },
      "score": {
        "away": 19,
        "home": 10
      },
      "state": {
        "down": 1,
        "offense": "away",
        "time": 2221,
        "yards to first down": 10,
        "yards to goal": 80
      }
    },
    {
      "number": 98,
      "play": {
        "type": "complete pass"
      },
      "score": {
        "away": 19,
        "home": 10
      },
      "state": {
        "down": 2,
        "offense": "away",
        "time": 2262,
        "yards to first down": 13,
        "yards to goal": 83
      }
    },
    {
      "number": 99,
      "play": {
        "type": "run"
      },
      "score": {
        "away": 19,
        "home": 10
      },
      "state": {
        "down": 1,
        "offense": "away",
        "time": 2294,
        "yards to first down": 10,
        "yards to goal": 70
      }
    },
    {
      "number": 100,
      "play": {
        "type": "run"
      },
      "score": {
        "away": 19,
        "home": 10
      },
      "state": {
        "down": 2,
        "offense": "away",
        "time": 2329,
        "yards to first down": 8,
        "yards to goal": 68
      }
    },
    {
      "number": 101,
      "play": {
        "type": "complete pass"
      },
      "score": {
        "away": 19,
        "home": 10
      },
      "state": {
        "down": 3,
        "offense": "away",
        "time": 2370,
        "yards to first down": 3,
        "yards to goal": 63
      }
    },
    {
      "number": 102,
      "play": {
        "type": "run"
      },
      "score": {
        "away": 19,
        "home": 10
      },
      "state": {
        "down": 1,
        "offense": "away",
        "time": 2412,
        "yards to first down": 10,
        "yards to goal": 58
      }
    },
    {
      "number": 103,
      "play": {
        "type": "run"
      },
      "score": {
        "away": 19,
        "home": 10
      },
      "state": {
        "down": 1,
        "offense": "away",
        "time": 2453,
        "yards to first down": 10,
        "yards to goal": 45
      }
    },
    {
      "number": 104,
      "play": {
        "type": "sack"
      },
      "score": {
        "away": 19,
        "home": 10
      },
      "state": {
        "down": 2,
        "offense": "away",
        "time": 2500,
        "yards to first down": 8,
        "yards to goal": 43
      }
    },
    {
      "number": 105,
      "play": {
        "type": "incomplete pass"
      },
      "score": {
        "away": 19,
        "home": 10
      },
      "state": {
        "down": 3,
        "offense": "away",
        "time": 2533,
        "yards to first down": 18,
        "yards to goal": 53
      }
    },
    {
      "number": 106,
      "play": {
        "type": "punt"
      },
      "score": {
        "away": 19,
        "home": 10
      },
      "state": {
        "down": 4,
        "offense": "away",
        "time": 2537,
        "yards to first down": 18,
        "yards to goal": 53
      }
    },
    {
      "number": 107,
      "play": {
        "type": "incomplete pass"
      },
      "score": {
        "away": 19,
        "home": 10
      },
      "state": {
        "down": 1,
        "offense": "home",
        "time": 2549,
        "yards to first down": 10,
        "yards to goal": 80
      }
    },
    {
      "number": 108,
      "play": {
        "type": "run"
      },
      "score": {
        "away": 19,
        "home": 10
      },
      "state": {
        "down": 2,
        "offense": "home",
        "time": 2555,
        "yards to first down": 10,
        "yards to goal": 80
      }
    },
    {
      "number": 109,
      "play": {
        "type": "sack"
      },
      "score": {
        "away": 19,
        "home": 10
      },
      "state": {
        "down": 3,
        "offense": "home",
        "time": 2596,
        "yards to first down": 6,
        "yards to goal": 76
      }
    },
    {
      "number": 110,
      "play": {
        "type": "punt"
      },
      "score": {
        "away": 19,
        "home": 10
      },
      "state": {
        "down": 4,
        "offense": "home",
        "time": 2623,
        "yards to first down": 19,
        "yards to goal": 89
      }
    },
    {
      "number": 111,
      "play": {
        "type": "run"
      },
      "score": {
        "away": 19,
        "home": 10
      },
      "state": {
        "down": 1,
        "offense": "away",
        "time": 2633,
        "yards to first down": 10,
        "yards to goal": 57
      }
    },
    {
      "number": 112,
      "play": {
        "type": "complete pass"
      },
      "score": {
        "away": 19,
        "home": 10
      },
      "state": {
        "down": 2,
        "offense": "away",
        "time": 2677,
        "yards to first down": 6,
        "yards to goal": 53
      }
    },
    {
      "number": 113,
      "play": {
        "type": "run"
      },
      "score": {
        "away": 19,
        "home": 10
      },
      "state": {
        "down": 1,
        "offense": "away",
        "time": 2700,
        "yards to first down": 10,
        "yards to goal": 42
      }
    },
    {
      "number": 114,
      "play": {
        "type": "run"
      },
      "score": {
        "away": 19,
        "home": 10
      },
      "state": {
        "down": 2,
        "offense": "away",
        "time": 2741,
        "yards to first down": 1,
        "yards to goal": 33
      }
    },
    {
      "number": 115,
      "play": {
        "type": "complete pass"
      },
      "score": {
        "away": 19,
        "home": 10
      },
      "state": {
        "down": 1,
        "offense": "away",
        "time": 2784,
        "yards to first down": 10,
        "yards to goal": 31
      }
    },
    {
      "number": 116,
      "play": {
        "type": "run"
      },
      "score": {
        "away": 19,
        "home": 10
      },
      "state": {
        "down": 1,
        "offense": "away",
        "time": 2818,
        "yards to first down": 10,
        "yards to goal": 20
      }
    },
    {
      "number": 117,
      "play": {
        "type": "complete pass"
      },
      "score": {
        "away": 19,
        "home": 10
      },
      "state": {
        "down": 2,
        "offense": "away",
        "time": 2858,
        "yards to first down": 9,
        "yards to goal": 19
      }
    },
    {
      "number": 118,
      "play": {
        "type": "incomplete pass"
      },
      "score": {
        "away": 19,
        "home": 10
      },
      "state": {
        "down": 3,
        "offense": "away",
        "time": 2893,
        "yards to first down": 5,
        "yards to goal": 15
      }
    },
    {
      "number": 119,
      "play": {
        "scoring": {
          "team": "away",
          "type": "field goal"
        },
        "type": "field goal"
      },
      "score": {
        "away": 22,
        "home": 10
      },
      "state": {
        "down": 4,
        "offense": "away",
        "time": 2898,
        "yards to first down": 5,
        "yards to goal": 15
      }
    },
    {
      "number": 120,
      "play": {
        "type": "kick off"
      },
      "score": {
        "away": 22,
        "home": 10
      },
      "state": {
        "offense": "home",
        "time": 2898,
        "yards to goal": 30
      }
    },
    {
      "number": 121,
      "play": {
        "type": "complete pass"
      },
      "score": {
        "away": 22,
        "home": 10
      },
      "state": {
        "down": 1,
        "offense": "home",
        "time": 2908,
        "yards to first down": 10,
        "yards to goal": 60
      }
    },
    {
      "number": 122,
      "play": {
        "type": "run"
      },
      "score": {
        "away": 22,
        "home": 10
      },
      "state": {
        "down": 2,
        "offense": "home",
        "time": 2943,
        "yards to first down": 2,
        "yards to goal": 52
      }
    },
    {
      "number": 123,
      "play": {
        "type": "incomplete pass"
      },
      "score": {
        "away": 22,
        "home": 10
      },
      "state": {
        "down": 1,
        "offense": "home",
        "time": 2981,
        "yards to first down": 10,
        "yards to goal": 49
      }
    },
    {
      "number": 124,
      "play": {
        "type": "run"
      },
      "score": {
        "away": 22,
        "home": 10
      },
      "state": {
        "down": 2,
        "offense": "home",
        "time": 2987,
        "yards to first down": 10,
        "yards to goal": 49
      }
    },
    {
      "number": 125,
      "play": {
        "type": "complete pass"
      },
      "score": {
        "away": 22,
        "home": 10
      },
      "state": {
        "down": 3,
        "offense": "home",
        "time": 3030,
        "yards to first down": 7,
        "yards to goal": 46
      }
    },
    {
      "number": 126,
      "play": {
        "scoring": {
          "team": "home",
          "type": "touchdown"
        },
        "type": "complete pass"
      },
      "score": {
        "away": 22,
        "home": 16
      },
      "state": {
        "down": 4,
        "offense": "home",
        "time": 3059,
        "yards to first down": 3,
        "yards to goal": 42
      }
    },
    {
      "number": 127,
      "play": {
        "scoring": {
          "team": "home",
          "type": "extra point"
        },
        "type": "extra point"
      },
      "score": {
        "away": 22,
        "home": 17
      },
      "state": {
        "offense": "home",
        "time": 3059
      }
    },
    {
      "number": 128,
      "penalty": {
        "no play": false,
        "penalties": [
          {
            "accepted": true,
            "name": "Offensive Holding",
            "offender": "Chris Hope",
            "team": "away",
            "yards": 10
          }
        ]
      },
      "play": {
        "type": "kick off"
      },
      "score": {
        "away": 22,
        "home": 17
      },
      "state": {
        "offense": "away",
        "time": 3059,
        "yards to goal": 30
      }
    },
    {
      "number": 129,
      "play": {
        "type": "complete pass"
      },
      "score": {
        "away": 22,
        "home": 17
      },
      "state": {
        "down": 1,
        "offense": "away",
        "time": 3069,
        "yards to first down": 10,
        "yards to goal": 75
      }
    },
    {
      "number": 130,
      "play": {
        "type": "complete pass"
      },
      "score": {
        "away": 22,
        "home": 17
      },
      "state": {
        "down": 2,
        "offense": "away",
        "time": 3107,
        "yards to first down": 5,
        "yards to goal": 70
      }
    },
    {
      "number": 131,
      "play": {
        "type": "run"
      },
      "score": {
        "away": 22,
        "home": 17
      },
      "state": {
        "down": 1,
        "offense": "away",
        "time": 3151,
        "yards to first down": 10,
        "yards to goal": 43
      }
    },
    {
      "number": 132,
      "play": {
        "type": "run"
      },
      "score": {
        "away": 22,
        "home": 17
      },
      "state": {
        "down": 2,
        "offense": "away",
        "time": 3200,
        "yards to first down": 6,
        "yards to goal": 39
      }
    },
    {
      "number": 133,
      "play": {
        "type": "run"
      },
      "score": {
        "away": 22,
        "home": 17
      },
      "state": {
        "down": 1,
        "offense": "away",
        "time": 3239,
        "yards to first down": 10,
        "yards to goal": 27
      }
    },
    {
      "number": 134,
      "play": {
        "type": "incomplete pass"
      },
      "score": {
        "away": 22,
        "home": 17
      },
      "state": {
        "down": 2,
        "offense": "away",
        "time": 3281,
        "yards to first down": 8,
        "yards to goal": 25
      }
    },
    {
      "number": 135,
      "play": {
        "type": "sack"
      },
      "score": {
        "away": 22,
        "home": 17
      },
      "state": {
        "down": 3,
        "offense": "away",
        "time": 3286,
        "yards to first down": 8,
        "yards to goal": 25
      }
    },
    {
      "number": 136,
      "play": {
        "scoring": {
          "team": "away",
          "type": "field goal"
        },
        "type": "field goal"
      },
      "score": {
        "away": 25,
        "home": 17
      },
      "state": {
        "down": 4,
        "offense": "away",
        "time": 3324,
        "yards to first down": 15,
        "yards to goal": 32
      }
    },
    {
      "number": 137,
      "play": {
        "type": "kick off"
      },
      "score": {
        "away": 25,
        "home": 17
      },
      "state": {
        "offense": "home",
        "time": 3324,
        "yards to goal": 30
      }
    },
    {
      "number": 138,
      "play": {
        "type": "run"
      },
      "score": {
        "away": 25,
        "home": 17
      },
      "state": {
        "down": 1,
        "offense": "home",
        "time": 3338,
        "yards to first down": 10,
        "yards to goal": 65
      }
    },
    {
      "number": 139,
      "play": {
        "type": "complete pass"
      },
      "score": {
        "away": 25,
        "home": 17
      },
      "state": {
        "down": 2,
        "offense": "home",
        "time": 3376,
        "yards to first down": 6,
        "yards to goal": 61
      }
    },
    {
      "number": 140,
      "play": {
        "type": "complete pass"
      },
      "score": {
        "away": 25,
        "home": 17
      },
      "state": {
        "down": 3,
        "offense": "home",
        "time": 3415,
        "yards to first down": 1,
        "yards to goal": 56
      }
    },
    {
      "number": 141,
      "play": {
        "type": "incomplete pass"
      },
      "score": {
        "away": 25,
        "home": 17
      },
      "state": {
        "down": 1,
        "offense": "home",
        "time": 3456,
        "yards to first down": 10,
        "yards to goal": 44
      }
    },
    {
      "number": 142,
      "play": {
        "type": "run"
      },
      "score": {
        "away": 25,
        "home": 17
      },
      "state": {
        "down": 2,
        "offense": "home",
        "time": 3467,
        "yards to first down": 10,
        "yards to goal": 44
      }
    },
    {
      "number": 143,
      "play": {
        "type": "run"
      },
      "score": {
        "away": 25,
        "home": 17
      },
      "state": {
        "down": 1,
        "offense": "home",
        "time": 3474,
        "yards to first down": 10,
        "yards to goal": 33
      }
    },
    {
      "number": 144,
      "play": {
        "type": "incomplete pass"
      },
      "score": {
        "away": 25,
        "home": 17
      },
      "state": {
        "down": 2,
        "offense": "home",
        "time": 3480,
        "yards to first down": 7,
        "yards to goal": 30
      }
    },
    {
      "number": 145,
      "penalty": {
        "no play": true,
        "penalties": [
          {
            "accepted": true,
            "name": "Illegal Contact",
            "offender": "Chad Scott",
            "team": "away",
            "yards": 5
          }
        ]
      },
      "play": {
        "type": "sack"
      },
      "score": {
        "away": 25,
        "home": 17
      },
      "state": {
        "down": 3,
        "offense": "home",
        "time": 3487,
        "yards to first down": 7,
        "yards to goal": 30
      },
      "turnovers": [
        {
          "by": "home",
          "recovered": "home",
          "type": "fumble"
        }
      ]
    },
    {
      "number": 146,
      "play": {
        "type": "run"
      },
      "score": {
        "away": 25,
        "home": 17
      },
      "state": {
        "down": 1,
        "offense": "home",
        "time": 3507,
        "yards to first down": 10,
        "yards to goal": 25
      }
    },
    {
      "number": 147,
      "play": {
        "type": "timeout"
      },
      "score": {
        "away": 25,
        "home": 17
      },
      "state": {
        "offense": "home",
        "time": 3520
      }
    },
    {
      "number": 148,
      "play": {
        "scoring": {
          "team": "home",
          "type": "touchdown"
        },
        "type": "complete pass"
      },
      "score": {
        "away": 25,
        "home": 23
      },
      "state": {
        "down": 1,
        "offense": "home",
        "time": 3521,
        "yards to first down": 7,
        "yards to goal": 7
      }
    },
    {
      "number": 149,
      "play": {
        "type": "two point conversion with incomplete pass"
      },
      "score": {
        "away": 25,
        "home": 23
      },
      "state": {
        "offense": "home",
        "time": 3521
      }
    },
    {
      "number": 150,
      "penalty": {
        "no play": true,
        "penalties": [
          {
            "accepted": true,
            "name": "Defensive Offside",
            "offender": "Mike Jones",
            "team": "home",
            "yards": 5
          }
        ]
      },
      "play": {
        "type": "penalty"
      },
      "score": {
        "away": 25,
        "home": 23
      },
      "state": {
        "offense": "away",
        "time": 3521
      }
    },
    {
      "number": 151,
      "penalty": {
        "no play": false,
        "penalties": [
          {
            "accepted": false,
            "name": "Offensive Offside",
            "offender": "Micah Ross",
            "team": "away"
          }
        ]
      },
      "play": {
        "type": "onside kick"
      },
      "score": {
        "away": 25,
        "home": 23
      },
      "state": {
        "offense": "away",
        "time": 3521,
        "yards to goal": 35
      }
    },
    {
      "number": 152,
      "play": {
        "type": "run"
      },
      "score": {
        "away": 25,
        "home": 23
      },
      "state": {
        "down": 1,
        "offense": "away",
        "time": 3526,
        "yards to first down": 10,
        "yards to goal": 48
      }
    },
    {
      "number": 153,
      "play": {
        "type": "timeout"
      },
      "score": {
        "away": 25,
        "home": 23
      },
      "state": {
        "offense": "away",
        "time": 3529
      }
    },
    {
      "number": 154,
      "play": {
        "type": "run"
      },
      "score": {
        "away": 25,
        "home": 23
      },
      "state": {
        "down": 2,
        "offense": "away",
        "time": 3529,
        "yards to first down": 11,
        "yards to goal": 49
      }
    },
    {
      "number": 155,
      "play": {
        "type": "run"
      },
      "score": {
        "away": 25,
        "home": 23
      },
      "state": {
        "down": 3,
        "offense": "away",
        "time": 3567,
        "yards to first down": 12,
        "yards to goal": 50
      }
    }
  ],
  "team stats": {
    "away": {
      "first downs": 23,
      "fumbles": {
        "lost": 0,
        "plays": 0
      },
      "pass": {
        "interceptions": 1,
        "plays": 27,
        "successful": 17,
        "touchdowns": 0,
        "yards": 201
      },
      "penalties": {
        "plays": 4,
        "yards": -25
      },
      "rush": {
        "plays": 40,
        "touchdowns": 1,
        "yards": 219
      },
      "sacks": {
        "plays": 2,
        "yards": -17
      }
    },
    "home": {
      "first downs": 13,
      "fumbles": {
        "lost": 0,
        "plays": 0
      },
      "pass": {
        "interceptions": 0,
        "plays": 23,
        "successful": 12,
        "touchdowns": 2,
        "yards": 146
      },
      "penalties": {
        "plays": 0,
        "yards": 0
      },
      "rush": {
        "plays": 21,
        "touchdowns": 1,
        "yards": 102
      },
      "sacks": {
        "plays": 3,
        "yards": -22
      }
    }
  },
  "venue": {
    "dome": false,
    "stadium": "Alltel Stadium",
    "surface": "grass"
  },
  "weather": {
    "relative humidity": 0.65,
    "temperature": 55,
    "wind speed": 11
  }
}